{
  "concept_id": "implicit_differentiation",
  "subject": "high_school_math_5pt",
  "level": "5pt",
  "math_track": [
    "5pt"
  ],
  "title_en": "Implicit Differentiation",
  "title_he": "גזירה סתומה",
  "summary_en": "Differentiate curves defined implicitly, find tangent lines, and solve related-rates problems — core 5pt Bagrut calculus.",
  "summary_he": "גזירה של עקומות מוגדרות באופן סתום, משיקים ובעיות קצבי שינוי קשורים — ליבת חשבון 5 יח'.",
  "est_minutes": 25,
  "sections": [
    {
      "kind": "intro",
      "title_en": "Explicit vs implicit functions",
      "title_he": "פונקציה מפורשת מול סתומה",
      "body_en_md": "**Explicit:** $y = f(x)$ — $y$ is isolated (e.g. $y = x^2 + 1$).\n\n**Implicit:** $F(x, y) = 0$ — relationship not solved for $y$ (e.g. $x^2 + y^2 = r^2$).\n\nCircles, ellipses, and many curves are easier **implicitly**. The idea: differentiate **both sides** with respect to $x$, treating $y$ as a function of $x$.",
      "body_he_md": "**מפורשת:** $y = f(x)$.\n\n**סתומה:** $F(x, y) = 0$ — הקשר לא פתור ל-$y$ (למשל $x^2 + y^2 = r^2$).\n\nמעגלים, אליפסות ועקומות רבות קלים יותר **בצורה סתומה**. הרעיון: גזרו **שני אגפים** ב-$x$, מתייחסים ל-$y$ כפונקציה של $x$."
    },
    {
      "kind": "theory",
      "title_en": "The chain rule for $\\frac{d}{dx}[g(y)]$",
      "title_he": "כלל השרשרת ל-$\\frac{d}{dx}[g(y)]$",
      "body_en_md": "Since $y = y(x)$, by the chain rule:\n\n$$\\frac{d}{dx}[y^2] = 2y \\cdot \\frac{dy}{dx}, \\quad \\frac{d}{dx}[\\sin y] = \\cos y \\cdot \\frac{dy}{dx}.$$\n\n**General pattern:** $\\frac{d}{dx}[f(y)] = f'(y) \\cdot y'$.\n\nWrite $y' = \\frac{dy}{dx}$ for brevity. This is the **key step** in every implicit differentiation problem.",
      "body_he_md": "מכיוון ש-$y = y(x)$, לפי כלל השרשרת:\n\n$$\\frac{d}{dx}[y^2] = 2y \\cdot y', \\quad \\frac{d}{dx}[\\sin y] = \\cos y \\cdot y'.$$\n\n**כלל כללי:** $\\frac{d}{dx}[f(y)] = f'(y) \\cdot y'$.\n\nזה **השלב המפתח** בכל בעיית גזירה סתומה."
    },
    {
      "kind": "worked_example",
      "title_en": "Worked example: circle",
      "title_he": "דוגמה פתורה: מעגל",
      "body_en_md": "$x^2 + y^2 = 25$. Differentiate:\n\n$$2x + 2y \\cdot y' = 0 \\Rightarrow y' = -\\frac{x}{y}.$$\n\n**Tangent at $(3, 4)$:** slope $= -\\frac{3}{4}$.\n\n$$y - 4 = -\\frac{3}{4}(x - 3).$$\n\n**Geometric check:** radius from origin to $(3,4)$ has slope $\\frac{4}{3}$; tangent slope $-\\frac{3}{4}$ — **perpendicular** ✓.",
      "body_he_md": "$x^2 + y^2 = 25$. גזירה:\n\n$$2x + 2y \\cdot y' = 0 \\Rightarrow y' = -\\frac{x}{y}.$$\n\n**משיק ב-$(3, 4)$:** שיפוע $= -\\frac{3}{4}$.\n\n$$y - 4 = -\\frac{3}{4}(x - 3).$$\n\n**בדיקה גאומטרית:** רדיוס ⟂ משיק ✓."
    },
    {
      "kind": "worked_example",
      "title_en": "More worked examples",
      "title_he": "דוגמאות נוספות",
      "body_en_md": "**Folium of Descartes:** $x^3 + y^3 = 6xy$.\n\n$$3x^2 + 3y^2 y' = 6y + 6xy' \\Rightarrow y' = \\frac{2y - x^2}{y^2 - 2x}.$$\n\n**Ellipse** $\\frac{x^2}{9} + \\frac{y^2}{4} = 1$ at $\\left(\\frac{3}{\\sqrt{2}}, \\sqrt{2}\\right)$:\n\nImplicit diff: $\\frac{2x}{9} + \\frac{2y}{4}y' = 0$ → $y' = -\\frac{4x}{9y}$.\n\nAt the point: $y' = -\\frac{4 \\cdot 3/\\sqrt{2}}{9\\sqrt{2}} = -\\frac{2}{3}$.",
      "body_he_md": "**עליון של דקארט:** $x^3 + y^3 = 6xy$ → $y' = \\frac{2y - x^2}{y^2 - 2x}$.\n\n**אליפסה** $\\frac{x^2}{9} + \\frac{y^2}{4} = 1$ ב-$\\left(\\frac{3}{\\sqrt{2}}, \\sqrt{2}\\right)$:\n\n$y' = -\\frac{4x}{9y} = -\\frac{2}{3}$."
    },
    {
      "kind": "summary",
      "title_en": "Related rates",
      "title_he": "קצבי שינוי קשורים",
      "body_en_md": "When variables depend on time $t$, differentiate with respect to $t$:\n\n**Ladder problem:** 10 m ladder, foot slides away at 2 m/s. How fast does the top slide down when foot is 6 m from wall?\n\n$x^2 + y^2 = 100$. Differentiate w.r.t. $t$:\n\n$$2x\\dot{x} + 2y\\dot{y} = 0 \\Rightarrow \\dot{y} = -\\frac{x}{y}\\dot{x}.$$\n\nAt $x = 6$: $y = 8$, $\\dot{x} = 2$ → $\\dot{y} = -\\frac{6}{8}(2) = -1.5$ m/s (top slides **down** at 1.5 m/s).",
      "body_he_md": "כשמשתנים תלויים בזמן $t$, גזרו ב-$t$:\n\n**בעיית הסולם:** סולם 10 מ', בסיס זז 2 מ'/ש'. כמה מהר הראש יורד כשהבסיס 6 מ' מהקיר?\n\n$x^2 + y^2 = 100$ → $2x\\dot{x} + 2y\\dot{y} = 0$.\n\nב-$x = 6$, $y = 8$, $\\dot{x} = 2$ → $\\dot{y} = -1.5$ מ'/ש'."
    },
    {
      "kind": "practice_tip",
      "title_en": "Exam-Style Practice Problems",
      "title_he": "תרגול בסגנון בחינה",
      "body_en_md": "### How to approach Bagrut-style questions\n\nIn the Bagrut exam, you will see multi-part questions (a, b, c) where each part builds on the previous. You must:\n- **Show all steps** — the examiner grades your process, not just the answer\n- **Write complete sentences** for proofs and justifications\n- **Check your answer** makes sense before moving on\n\n---\n\n**Practice Problem 1:**\n\nFind all $x\\in[0,2\\pi]$ where $2\\sin^2 x - \\sin x - 1 = 0$.\n\n**Complete Solution:**\n\nLet $u=\\sin x$: $2u^2-u-1=0$ → $(2u+1)(u-1)=0$ → $u=1$ or $u=-\\frac{1}{2}$.\n$\\sin x=1$ → $x=\\frac{\\pi}{2}$. $\\sin x=-\\frac{1}{2}$ → $x=\\frac{7\\pi}{6},\\frac{11\\pi}{6}$.\n\n---\n\n**Practice Problem 2:**\n\nFind $\\frac{dy}{dx}$ if $x^2+y^2=25$ at $(3,4)$.\n\n**Complete Solution:**\n\n$2x+2y\\frac{dy}{dx}=0$ → $\\frac{dy}{dx}=-\\frac{x}{y}=-\\frac{3}{4}$.",
      "body_he_md": "### איך לגשת לשאלות בסגנון בגרות\n\nבבחינת הבגרות תראו שאלות רב-סעיפיות (א, ב, ג) שכל סעיף נשען על הקודם. חובה:\n- **להראות את כל השלבים** — הבוחן מדרג את הדרך, לא רק את התשובה\n- **לכתוב משפטים מלאים** בהוכחות ובנימוקים\n- **לבדוק שהתשובה הגיונית** לפני שממשיכים\n\n---\n\n**שאלת תרגול 1:**\n\nכל $x\\in[0,2\\pi]$: $2\\sin^2 x-\\sin x-1=0$.\n\n**פתרון:** $x=\\frac{\\pi}{2},\\frac{7\\pi}{6},\\frac{11\\pi}{6}$.\n\n---\n\n**שאלת תרגול 2:**\n\n$x^2+y^2=25$ ב-$(3,4)$: $\\frac{dy}{dx}=-\\frac{3}{4}$."
    }
  ],
  "questions": [
    {
      "ord": 1,
      "kind": "mcq",
      "difficulty": "easy",
      "stem_en": "If $x^2 + y^2 = 16$, what is $\\frac{dy}{dx}$?",
      "stem_he": "אם $x^2 + y^2 = 16$, מה $\\frac{dy}{dx}$?",
      "options_en": [
        "$-\\frac{x}{y}$",
        "$\\frac{x}{y}$",
        "$-\\frac{y}{x}$",
        "$2x + 2y$"
      ],
      "options_he": [
        "$-\\frac{x}{y}$",
        "$\\frac{x}{y}$",
        "$-\\frac{y}{x}$",
        "$2x + 2y$"
      ],
      "correct_index": 0,
      "explanation_en": "$2x + 2yy' = 0$ → $y' = -x/y$.",
      "explanation_he": "$2x + 2yy' = 0$ → $y' = -x/y$."
    },
    {
      "ord": 2,
      "kind": "mcq",
      "difficulty": "medium",
      "stem_en": "Slope of tangent to $x^2 + y^2 = 25$ at $(3, 4)$:",
      "stem_he": "שיפוע משיק ל-$x^2 + y^2 = 25$ ב-$(3, 4)$:",
      "options_en": [
        "$\\frac{3}{4}$",
        "$-\\frac{3}{4}$",
        "$-\\frac{4}{3}$",
        "$\\frac{4}{3}$"
      ],
      "options_he": [
        "$\\frac{3}{4}$",
        "$-\\frac{3}{4}$",
        "$-\\frac{4}{3}$",
        "$\\frac{4}{3}$"
      ],
      "correct_index": 1,
      "explanation_en": "$y' = -x/y = -3/4$.",
      "explanation_he": "$y' = -3/4$."
    },
    {
      "ord": 3,
      "kind": "mcq",
      "difficulty": "hard",
      "stem_en": "For $x^3 + y^3 = 3xy$, find $y'$:",
      "stem_he": "ל-$x^3 + y^3 = 3xy$, מצאו $y'$:",
      "options_en": [
        "$\\frac{y - x^2}{y^2 - x}$",
        "$\\frac{y - x^2}{y^2 - 2x}$",
        "$\\frac{x^2 - y}{y^2 - x}$",
        "$\\frac{2y - x^2}{y^2 - 2x}$"
      ],
      "options_he": [
        "$\\frac{y - x^2}{y^2 - x}$",
        "$\\frac{y - x^2}{y^2 - 2x}$",
        "$\\frac{x^2 - y}{y^2 - x}$",
        "$\\frac{2y - x^2}{y^2 - 2x}$"
      ],
      "correct_index": 3,
      "explanation_en": "Collect $y'$ terms: $y'(3y^2 - 6x) = 6y - 3x^2$.",
      "explanation_he": "איסוף $y'$: $y'(3y^2 - 6x) = 6y - 3x^2$."
    },
    {
      "ord": 4,
      "kind": "open",
      "difficulty": "hard",
      "stem_en": "Prove by mathematical induction:\n$$\\sum_{k=1}^{n} k^2 = \\frac{n(n+1)(2n+1)}{6}$$",
      "stem_he": "הוכיחו באינדוקציה:\n$$\\sum_{k=1}^{n} k^2 = \\frac{n(n+1)(2n+1)}{6}$$",
      "rubric_en": "2pts base; 3pts hypothesis; 5pts inductive algebra.",
      "rubric_he": "2 נק' בסיס; 3 נק' הנחה; 5 נק' צעד.",
      "explanation_en": "Standard induction: base OK; inductive step factors to required form.",
      "explanation_he": "אינדוקציה סטנדרטית — בסיס וצעד.",
      "skill_atoms": [
        "exam_practice"
      ],
      "points_level_min": "hs_math_5pt"
    },
    {
      "ord": 5,
      "kind": "open",
      "difficulty": "hard",
      "stem_en": "Find all $x\\in[0,2\\pi]$ satisfying $2\\sin^2 x - \\sin x - 1 = 0$. Show all work.",
      "stem_he": "מצאו כל $x\\in[0,2\\pi]$: $2\\sin^2 x - \\sin x - 1 = 0$. הראו שלבים.",
      "rubric_en": "3pts substitution; 4pts solving trig; 3pts all solutions in interval.",
      "rubric_he": "3 נק' הצבה; 4 נק' טrig; 3 נק' כל הפתרונות.",
      "explanation_en": "x = π/2, 7π/6, 11π/6.",
      "explanation_he": "x = π/2, 7π/6, 11π/6.",
      "skill_atoms": [
        "exam_practice"
      ],
      "points_level_min": "hs_math_5pt"
    }
  ],
  "agent_hints": "Students forget the y' factor when differentiating g(y). Always collect y' terms on one side. For tangents, verify perpendicularity to radius on circles. Related rates: draw diagram, label rates, differentiate w.r.t. t, then substitute. Prerequisite: lesson:derivatives_intro chain rule."
}
