{
  "concept_id": "matrix_representation",
  "subject": "math",
  "level": "university",
  "title_en": "Matrix Representation of Linear Maps",
  "title_he": "ייצוג מטריציוני של העתקות לינאריות",
  "summary_en": "Matrix representation of a linear map relative to a basis. Change of basis formula. Similarity and diagonalization connection.",
  "summary_he": "ייצוג מטריציוני של העתקה לינארית יחסית לבסיס. נוסחת שינוי בסיס. קשר לדמיון ואלכסון.",
  "est_minutes": 45,
  "sections": [
    {
      "kind": "intro",
      "title_en": "Why Basis Matters",
      "title_he": "מדוע הבסיס חשוב",
      "body_en_md": "A linear transformation $T:V\\to V$ is an abstract object. To compute with it, we need **coordinates** — which depend on a chosen basis.\n\nThe same transformation can have very different matrix representations in different bases. The right choice of basis can simplify the matrix dramatically (e.g., to diagonal form).\n\nThis is the bridge between abstract linear algebra and computational linear algebra.",
      "body_he_md": "טרנספורמציה $T$ היא אובייקט אבסטרקטי. לחישוב נדרשות **קואורדינטות** — התלויות בבחירת הבסיס.\n\nאותה טרנספורמציה עשויה להיראות שונה מאוד בבסיסים שונים. בחירה נכונה פשטת את המטריצה (ייאלכסון)."
    },
    {
      "kind": "definition",
      "title_en": "Matrix of a Linear Map Relative to a Basis",
      "title_he": "מטריצת העתקה ביחס לבסיס",
      "body_en_md": "Let $V$ be an $n$-dim space with basis $B=\\{v_1,\\ldots,v_n\\}$, $T:V\\to V$.\n\n**Coordinate vector:** $[v]_B=$ coefficients of $v$ in basis $B$.\n\n**Matrix of $T$ in basis $B$:**\n$$[T]_B = \\bigl([T(v_1)]_B \\mid [T(v_2)]_B \\mid \\cdots \\mid [T(v_n)]_B\\bigr)$$\n\n(Column $j$ = coordinate vector of $T(v_j)$ in $B$.)\n\n**Then:** $[T(v)]_B = [T]_B \\cdot [v]_B$.\n\n**Change of basis:** If $P$ = change-of-basis matrix from $B$ to $C$, and $[T]_B$ is known:\n$$[T]_C = P^{-1}[T]_B P.$$",
      "body_he_md": "**מטריצת $T$ בבסיס $B$:** עמודה $j$ = $[T(v_j)]_B$.\n\n**שינוי בסיס:** $[T]_C=P^{-1}[T]_B P$. (מטריצות **דומות**.)"
    },
    {
      "kind": "theory",
      "title_en": "Change-of-Basis Matrix and Similarity",
      "title_he": "מטריצת מעבר ודמיון",
      "body_en_md": "**Transition matrix $P$ from $B$ to standard basis $E$:**\n$$P = [v_1 | v_2 | \\cdots | v_n]$$\n(columns = basis vectors of $B$ in standard coordinates).\n\n**Similarity:** $A$ and $B$ are **similar** if $B=P^{-1}AP$ for some invertible $P$. Similar matrices represent the same linear map in different bases.\n\n**Invariants under similarity:** trace, determinant, eigenvalues, rank, characteristic polynomial.\n\n**Goal:** Find a basis in which $[T]_B$ is diagonal (if $T$ is diagonalizable) — this is the eigenvector basis!",
      "body_he_md": "**מטריצת מעבר $P$ מ-$B$ לסטנדרטי:** עמודות = וקטורי הבסיס $B$.\n\n**דמיון:** $B=P^{-1}AP$. מטריצות דומות — אותה העתקה, בסיס שונה.\n\n**אינוואריאנטים:** עקבה, דטרמיננט, ערכים עצמיים.\n\n**מטרה:** מצא בסיס שבו $[T]$ אלכסוני = בסיס וקטורים עצמיים."
    },
    {
      "kind": "worked_example",
      "difficulty": "easy",
      "example_number": 1,
      "title_en": "Worked Example 1 — Matrix in a New Basis",
      "title_he": "דוגמה פתורה 1 — מטריצה בבסיס חדש",
      "body_en_md": "**$T:\\mathbb{R}^2\\to\\mathbb{R}^2$:** $T(x,y)=(x+y, x-y)$. Standard basis $E$: $[T]_E=\\begin{pmatrix}1&1\\\\1&-1\\end{pmatrix}$.\n\n**New basis $B=\\{v_1,v_2\\}$** with $v_1=(1,1)^T$, $v_2=(1,-1)^T$.\n\n$T(v_1)=T(1,1)=(2,0)=[T]_E v_1$. In basis $B$: $[T(v_1)]_B=?$ We need to express $(2,0)$ as $\\alpha(1,1)+\\beta(1,-1)$: $\\alpha+\\beta=2$, $\\alpha-\\beta=0$. $\\alpha=1$, $\\beta=1$. $[T(v_1)]_B=(1,1)^T$.\n\n$T(v_2)=T(1,-1)=(0,2)$. Express: $\\alpha(1,1)+\\beta(1,-1)=(0,2)$. $\\alpha=1$, $\\beta=-1$. $[T(v_2)]_B=(1,-1)^T$.\n\n$[T]_B=\\begin{pmatrix}1&1\\\\1&-1\\end{pmatrix}$. (Same as $E$ in this case — a coincidence.)",
      "body_he_md": "$[T(v_1)]_B=(1,1)^T$, $[T(v_2)]_B=(1,-1)^T$.\n$[T]_B=\\begin{pmatrix}1&1\\\\1&-1\\end{pmatrix}$."
    },
    {
      "kind": "checkpoint",
      "title_en": "Stop & Practice",
      "title_he": "עצור ותרגל",
      "body_en_md": "What is the transition matrix $P$ from basis $B=\\{(1,1)^T,(1,-1)^T\\}$ to standard?",
      "body_he_md": "מהי מטריצת המעבר $P$ מבסיס $B=\\{(1,1)^T,(1,-1)^T\\}$ לסטנדרטי?",
      "checkpoint_solution_en": "$P=[v_1|v_2]=\\begin{pmatrix}1&1\\\\1&-1\\end{pmatrix}$.",
      "checkpoint_solution_he": "$P=\\begin{pmatrix}1&1\\\\1&-1\\end{pmatrix}$."
    },
    {
      "kind": "worked_example",
      "difficulty": "medium",
      "example_number": 2,
      "title_en": "Worked Example 2 — Change of Basis Formula",
      "title_he": "דוגמה פתורה 2 — נוסחת שינוי בסיס",
      "body_en_md": "**$T:\\mathbb{R}^2\\to\\mathbb{R}^2$** with $[T]_E=\\begin{pmatrix}2&1\\\\0&3\\end{pmatrix}$.\n\nNew basis $B=\\{(1,0)^T,(1,1)^T\\}$.\n\n$P=\\begin{pmatrix}1&1\\\\0&1\\end{pmatrix}$.\n\n$P^{-1}=\\begin{pmatrix}1&-1\\\\0&1\\end{pmatrix}$.\n\n$[T]_B=P^{-1}[T]_E P=\\begin{pmatrix}1&-1\\\\0&1\\end{pmatrix}\\begin{pmatrix}2&1\\\\0&3\\end{pmatrix}\\begin{pmatrix}1&1\\\\0&1\\end{pmatrix}$\n\n$=\\begin{pmatrix}2&-2\\\\0&3\\end{pmatrix}\\begin{pmatrix}1&1\\\\0&1\\end{pmatrix}=\\begin{pmatrix}2&0\\\\0&3\\end{pmatrix}$.\n\nThe matrix became **diagonal** — because $B$ is the eigenvector basis!",
      "body_he_md": "$[T]_B=P^{-1}[T]_EP=\\begin{pmatrix}2&0\\\\0&3\\end{pmatrix}$ — המטריצה התאלכסנה!"
    },
    {
      "kind": "checkpoint",
      "title_en": "Stop & Practice",
      "title_he": "עצור ותרגל",
      "body_en_md": "Two matrices $A$ and $B=P^{-1}AP$ are similar. Do they have the same eigenvalues?",
      "body_he_md": "$A$ ו-$B=P^{-1}AP$ דומות. האם להן אותם ערכים עצמיים?",
      "checkpoint_solution_en": "Yes. Similar matrices have the same characteristic polynomial, hence the same eigenvalues.",
      "checkpoint_solution_he": "כן. למטריצות דומות פולינום מאפיין זהה → ערכים עצמיים זהים."
    },
    {
      "kind": "worked_example",
      "difficulty": "hard",
      "example_number": 3,
      "title_en": "Worked Example 3 — Finding Diagonalizing Basis",
      "title_he": "דוגמה פתורה 3 — מציאת בסיס מאלכסן",
      "body_en_md": "**$A=\\begin{pmatrix}4&1\\\\2&3\\end{pmatrix}$. Find basis $B$ so that $[T]_B$ is diagonal.**\n\n**Step 1:** Eigenvalues: $\\det(A-\\lambda I)=(4-\\lambda)(3-\\lambda)-2=\\lambda^2-7\\lambda+10=(\\lambda-5)(\\lambda-2)=0$. $\\lambda_1=5$, $\\lambda_2=2$.\n\n**Step 2:** Eigenvectors:\n- $\\lambda_1=5$: $(A-5I)v=0$: $\\begin{pmatrix}-1&1\\\\2&-2\\end{pmatrix}\\to v_1=(1,1)^T$.\n- $\\lambda_2=2$: $(A-2I)v=0$: $\\begin{pmatrix}2&1\\\\2&1\\end{pmatrix}\\to v_2=(1,-2)^T$.\n\n**Step 3:** Basis $B=\\{v_1,v_2\\}$.\n$$[T]_B=P^{-1}AP=\\begin{pmatrix}5&0\\\\0&2\\end{pmatrix}.$$",
      "body_he_md": "$\\lambda_1=5$: $v_1=(1,1)^T$. $\\lambda_2=2$: $v_2=(1,-2)^T$.\n$P=[v_1|v_2]$. $[T]_B=P^{-1}AP=\\begin{pmatrix}5&0\\\\0&2\\end{pmatrix}$."
    },
    {
      "kind": "method_guide",
      "title_en": "Method Guide — Matrix Representation",
      "title_he": "מדריך שיטה — ייצוג מטריציוני",
      "body_en_md": "**Matrix of $T$ in basis $B$:**\n1. Apply $T$ to each basis vector: compute $T(v_j)$.\n2. Express each $T(v_j)$ as a linear combination in basis $B$.\n3. Put coefficients as columns → $[T]_B$.\n\n**Change of basis:**\n1. Form $P=[v_1|\\cdots|v_n]$ (B-to-standard).\n2. Compute $P^{-1}$.\n3. $[T]_C=P^{-1}[T]_EP$.\n\n**Diagonalization:**\n1. Find eigenvalues: $\\det(A-\\lambda I)=0$.\n2. Find eigenvectors for each.\n3. $P=[e_1|e_2|\\cdots]$, $D=P^{-1}AP$ = diagonal matrix.",
      "body_he_md": "**מטריצה בבסיס $B$:** הפעל $T$ על בסיס, בטא בקואורדינטות $B$.\n\n**שינוי בסיס:** $[T]_C=P^{-1}[T]_EP$.\n\n**אלכסון:** ערכים עצמיים → וקטורים עצמיים → $P$."
    },
    {
      "kind": "exercise_set",
      "title_en": "Practice Exercises",
      "title_he": "תרגילים",
      "body_en_md": "", "body_he_md": "",
      "exercises": [
        {"id":"e1","difficulty":"easy","body_en":"$T(e_1)=2e_1$, $T(e_2)=3e_2$. Matrix of $T$ in standard basis?","body_he":"$T(e_1)=2e_1$, $T(e_2)=3e_2$. מטריצה?","solution_en":"$[T]_E=\\begin{pmatrix}2&0\\\\0&3\\end{pmatrix}$.","solution_he":"$\\begin{pmatrix}2&0\\\\0&3\\end{pmatrix}$."},
        {"id":"e2","difficulty":"easy","body_en":"Transition matrix from $B=\\{(2,0)^T,(0,3)^T\\}$ to standard?","body_he":"מטריצת מעבר מ-$B=\\{(2,0)^T,(0,3)^T\\}$ לסטנדרטי?","solution_en":"$P=\\begin{pmatrix}2&0\\\\0&3\\end{pmatrix}$.","solution_he":"$P=\\begin{pmatrix}2&0\\\\0&3\\end{pmatrix}$."},
        {"id":"e3","difficulty":"easy","body_en":"Similar matrices have the same determinant. True or false?","body_he":"למטריצות דומות $\\det$ זהה. נכון?","solution_en":"True: $\\det(P^{-1}AP)=\\det(P^{-1})\\det(A)\\det(P)=\\det(A)$.","solution_he":"נכון: $\\det(P^{-1}AP)=\\det(A)$."},
        {"id":"e4","difficulty":"easy","body_en":"What does it mean for two matrices to be similar?","body_he":"מתי שתי מטריצות דומות?","solution_en":"$A\\sim B$ if $B=P^{-1}AP$ for some invertible $P$. They represent the same linear map in different bases.","solution_he":"$B=P^{-1}AP$. אותה העתקה, בסיס שונה."},
        {"id":"e5","difficulty":"medium","body_en":"$[T]_E=\\begin{pmatrix}3&0\\\\0&5\\end{pmatrix}$, $P=\\begin{pmatrix}1&1\\\\0&1\\end{pmatrix}$. Find $[T]_B=P^{-1}[T]_EP$.","body_he":"חשב $[T]_B=P^{-1}[T]_EP$ עם $P=\\begin{pmatrix}1&1\\\\0&1\\end{pmatrix}$, $[T]_E=\\begin{pmatrix}3&0\\\\0&5\\end{pmatrix}$.","solution_en":"$P^{-1}=\\begin{pmatrix}1&-1\\\\0&1\\end{pmatrix}$. $P^{-1}[T]_E=\\begin{pmatrix}3&-5\\\\0&5\\end{pmatrix}$. $\\times P=\\begin{pmatrix}3&-2\\\\0&5\\end{pmatrix}$.","solution_he":"$\\begin{pmatrix}3&-2\\\\0&5\\end{pmatrix}$."},
        {"id":"e6","difficulty":"medium","body_en":"For $A=\\begin{pmatrix}1&2\\\\0&1\\end{pmatrix}$, find all $B$ similar to $A$ via $P=\\begin{pmatrix}1&1\\\\0&1\\end{pmatrix}$.","body_he":"$A=\\begin{pmatrix}1&2\\\\0&1\\end{pmatrix}$, $P=\\begin{pmatrix}1&1\\\\0&1\\end{pmatrix}$. חשב $B=P^{-1}AP$.","solution_en":"$P^{-1}=\\begin{pmatrix}1&-1\\\\0&1\\end{pmatrix}$. $P^{-1}A=\\begin{pmatrix}1&1\\\\0&1\\end{pmatrix}$. $\\times P=\\begin{pmatrix}1&2\\\\0&1\\end{pmatrix}$. Same as $A$ (since $A=P$, it commutes).","solution_he":"$B=A$ (מקרה מיוחד)."},
        {"id":"e7","difficulty":"medium","body_en":"Reflection $T$ over $y$-axis in $\\mathbb{R}^2$: $T(x,y)=(-x,y)$. Write $[T]_E$.","body_he":"שיקוף $T$ מעל ציר $y$: $T(x,y)=(-x,y)$. מטריצה?","solution_en":"$T(e_1)=(-1,0)$, $T(e_2)=(0,1)$. $[T]_E=\\begin{pmatrix}-1&0\\\\0&1\\end{pmatrix}$.","solution_he":"$\\begin{pmatrix}-1&0\\\\0&1\\end{pmatrix}$."},
        {"id":"e8","difficulty":"medium","body_en":"Rotation by $90°$ counterclockwise: $T(x,y)=(-y,x)$. Matrix?","body_he":"סיבוב ב-$90°$ נגד כיוון שעון: $T(x,y)=(-y,x)$. מטריצה?","solution_en":"$T(e_1)=(0,1)$, $T(e_2)=(-1,0)$. $[T]_E=\\begin{pmatrix}0&-1\\\\1&0\\end{pmatrix}$.","solution_he":"$\\begin{pmatrix}0&-1\\\\1&0\\end{pmatrix}$."},
        {"id":"e9","difficulty":"medium","body_en":"Similar matrices have the same eigenvalues. Why?","body_he":"למטריצות דומות ערכים עצמיים זהים. מדוע?","solution_en":"$\\det(P^{-1}AP-\\lambda I)=\\det(P^{-1}(A-\\lambda I)P)=\\det(A-\\lambda I)$. Same characteristic polynomial → same eigenvalues.","solution_he":"$\\det(P^{-1}AP-\\lambda I)=\\det(A-\\lambda I)$. אותו פולינום מאפיין."},
        {"id":"e10","difficulty":"hard","body_en":"$A=\\begin{pmatrix}0&1\\\\1&0\\end{pmatrix}$ (swap transformation). Find diagonalizing matrix $P$ and diagonal form.","body_he":"$A=\\begin{pmatrix}0&1\\\\1&0\\end{pmatrix}$. מצא $P$ ואלכסון.","solution_en":"Eigenvalues: $\\lambda^2-1=0$: $\\lambda=1,-1$. $v_1=(1,1)^T$ ($\\lambda=1$), $v_2=(1,-1)^T$ ($\\lambda=-1$). $P=\\begin{pmatrix}1&1\\\\1&-1\\end{pmatrix}$. $D=\\begin{pmatrix}1&0\\\\0&-1\\end{pmatrix}$.","solution_he":"$\\lambda=\\pm1$. $P=\\begin{pmatrix}1&1\\\\1&-1\\end{pmatrix}$. $D=\\begin{pmatrix}1&0\\\\0&-1\\end{pmatrix}$."},
        {"id":"e11","difficulty":"hard","body_en":"Express the coordinate vector of $v=(3,5)^T$ in basis $B=\\{(1,2)^T,(0,1)^T\\}$.","body_he":"בטא $v=(3,5)^T$ בבסיס $B=\\{(1,2)^T,(0,1)^T\\}$.","solution_en":"$3\\cdot(1,2)+b_2(0,1)=(3,5)$: $3=3$ ✓, $6+b_2=5\\Rightarrow b_2=-1$. Wait: $\\alpha(1,2)+\\beta(0,1)=(3,5)$: $\\alpha=3$, $2\\alpha+\\beta=5\\Rightarrow\\beta=-1$. $[v]_B=(3,-1)^T$.","solution_he":"$[v]_B=(3,-1)^T$."},
        {"id":"e12","difficulty":"hard","body_en":"$T$ has matrix $A=\\begin{pmatrix}5&-2\\\\3&0\\end{pmatrix}$ in standard basis. Compute $[T^2]_E$.","body_he":"$[T]_E=\\begin{pmatrix}5&-2\\\\3&0\\end{pmatrix}$. חשב $[T^2]_E$.","solution_en":"$A^2=\\begin{pmatrix}5&-2\\\\3&0\\end{pmatrix}^2=\\begin{pmatrix}25-6&-10\\\\15&-6\\end{pmatrix}=\\begin{pmatrix}19&-10\\\\15&-6\\end{pmatrix}$.","solution_he":"$A^2=\\begin{pmatrix}19&-10\\\\15&-6\\end{pmatrix}$."},
        {"id":"e13","difficulty":"hard","body_en":"Why is it useful to diagonalize a matrix?","body_he":"מדוע שימושי לאלכסן מטריצה?","solution_en":"Powers: $A^n=PD^nP^{-1}$ and $D^n$ is trivial. Solving ODEs. Computing matrix exponentials. Spectral analysis. All simplify dramatically with diagonal $D$.","solution_he":"$A^n=PD^nP^{-1}$, $D^n$ טריוויאלי. מועיל לחזקות, ОDEs, אקספוננט מטריציוני."}
      ]
    },
    {
      "kind": "pitfall",
      "title_en": "Common Pitfalls",
      "title_he": "מלכודות נפוצות",
      "body_en_md": "1. **Column vs row in $[T]_B$**: columns = images of basis vectors in $B$, not rows.\n2. **$P$ direction**: $P$ from $B$ to standard means columns = $B$ vectors in standard coords.\n3. **Change of basis**: $[T]_C=P^{-1}[T]_BP$ — $P$ on the right, $P^{-1}$ on the left.\n4. **Not all matrices are diagonalizable**: requires $n$ independent eigenvectors.",
      "body_he_md": "1. **עמודות, לא שורות** ב-$[T]_B$.\n2. **כיוון $P$**: עמודות = וקטורי $B$ בקואורדינטות סטנדרטיות.\n3. **שינוי בסיס**: $P^{-1}AP$ (לא $PAP^{-1}$).\n4. **לא תמיד ניתן לאלכסן**: צריך $n$ וקטורים עצמיים עצמאיים."
    },
    {
      "kind": "before_exam",
      "title_en": "Before the Exam",
      "title_he": "לפני הבחינה",
      "body_en_md": "- $[T]_B$: column $j$ = $[T(v_j)]_B$.\n- Change of basis: $[T]_C=P^{-1}[T]_EP$.\n- $P$ = transition matrix = columns are $B$-vectors in standard coordinates.\n- Similar matrices: same eigenvalues, trace, determinant.\n- Diagonalize: $D=P^{-1}AP$ where $P$ = eigenvectors, $D$ = eigenvalues on diagonal.",
      "body_he_md": "- $[T]_B$: עמודה $j$ = $[T(v_j)]_B$.\n- שינוי: $P^{-1}[T]_EP$.\n- דומות: ערכים עצמיים, עקבה, $\\det$ זהים.\n- אלכסון: $D=P^{-1}AP$."
    },
    {
      "kind": "summary",
      "title_en": "Take-away",
      "title_he": "סיכום",
      "body_en_md": "- Matrix of $T$ depends on chosen basis.\n- Change of basis: $P^{-1}AP$.\n- Diagonalization: $P$ = eigenvectors, $D$ = eigenvalues.\n- Similar matrices = same transformation, different coordinates.",
      "body_he_md": "- מטריצה תלויה בבסיס.\n- שינוי: $P^{-1}AP$.\n- אלכסון: $P$ = וקטורים עצמיים, $D$ = ערכים עצמיים.\n- דומות = אותה העתקה, בסיס שונה."
    }
  ],
  "questions": [
    {"ord":1,"kind":"mcq","difficulty":"medium","stem_en":"$B=P^{-1}AP$ means $A$ and $B$ are:","stem_he":"$B=P^{-1}AP$: $A$ ו-$B$ הן:","options_en":["Orthogonal","Similar","Identical","Transpose of each other"],"options_he":["אורתוגונליות","דומות","זהות","חצי זו של זו"],"correct_index":1,"explanation_en":"$B=P^{-1}AP$ is the definition of similar matrices.","explanation_he":"$B=P^{-1}AP$ — הגדרת מטריצות דומות.","skill_atoms":["change_of_basis","similar_matrices"]}
  ],
  "agent_hints": {
    "key_insights": [
      "Matrix of T in basis B: column j = [T(v_j)]_B.",
      "Change of basis: [T]_C = P^{-1}[T]_E P.",
      "Similar matrices represent the same transformation in different bases.",
      "Diagonalization: P = eigenvectors, D = P^{-1}AP = diagonal eigenvalues."
    ],
    "common_misconceptions": [
      {"wrong": "Change of basis formula is PAP^{-1}","correction": "It is P^{-1}AP.","detect_phrase_en":"change basis PAP inverse","detect_phrase_he":"שינוי בסיס PAP הופכי"}
    ],
    "skill_atoms_unlocked": ["matrix_representation","change_of_basis","similar_matrices","diagonalization"],
    "tutor_pacing_hint": "Matrix in basis first, then transition matrix, then change-of-basis formula.",
    "next_recommended": ["la_eigenvalues","la_diagonalization"]
  }
}
